[
  {
    "date": "2025-11-25",
    "total": 60151,
    "formats": [
      {
        "ext": ".exe",
        "count": 39202
      },
      {
        "ext": ".asar",
        "count": 13007
      },
      {
        "ext": ".dmg",
        "count": 4007
      },
      {
        "ext": ".zip",
        "count": 2293
      },
      {
        "ext": ".sig",
        "count": 1122
      },
      {
        "ext": ".appimage",
        "count": 520
      }
    ]
  },
  {
    "date": "2025-11-26",
    "total": 60298,
    "formats": [
      {
        "ext": ".exe",
        "count": 39295
      },
      {
        "ext": ".asar",
        "count": 13007
      },
      {
        "ext": ".dmg",
        "count": 4036
      },
      {
        "ext": ".zip",
        "count": 2316
      },
      {
        "ext": ".sig",
        "count": 1122
      },
      {
        "ext": ".appimage",
        "count": 522
      }
    ]
  },
  {
    "date": "2025-11-27",
    "total": 60548,
    "formats": [
      {
        "ext": ".exe",
        "count": 39466
      },
      {
        "ext": ".asar",
        "count": 13007
      },
      {
        "ext": ".dmg",
        "count": 4084
      },
      {
        "ext": ".zip",
        "count": 2341
      },
      {
        "ext": ".sig",
        "count": 1122
      },
      {
        "ext": ".appimage",
        "count": 528
      }
    ]
  },
  {
    "date": "2025-11-28",
    "total": 60780,
    "formats": [
      {
        "ext": ".exe",
        "count": 39617
      },
      {
        "ext": ".asar",
        "count": 13007
      },
      {
        "ext": ".dmg",
        "count": 4089
      },
      {
        "ext": ".zip",
        "count": 2363
      },
      {
        "ext": ".sig",
        "count": 1122
      },
      {
        "ext": ".appimage",
        "count": 537
      },
      {
        "ext": ".rpm",
        "count": 41
      },
      {
        "ext": ".deb",
        "count": 4
      }
    ]
  },
  {
    "date": "2025-11-29",
    "total": 61241,
    "formats": [
      {
        "ext": ".exe",
        "count": 39881
      },
      {
        "ext": ".asar",
        "count": 13007
      },
      {
        "ext": ".dmg",
        "count": 4111
      },
      {
        "ext": ".zip",
        "count": 2418
      },
      {
        "ext": ".sig",
        "count": 1122
      },
      {
        "ext": ".appimage",
        "count": 552
      },
      {
        "ext": ".rpm",
        "count": 144
      },
      {
        "ext": ".deb",
        "count": 6
      }
    ]
  },
  {
    "date": "2025-11-30",
    "total": 61717,
    "formats": [
      {
        "ext": ".exe",
        "count": 40159
      },
      {
        "ext": ".asar",
        "count": 13007
      },
      {
        "ext": ".dmg",
        "count": 4122
      },
      {
        "ext": ".zip",
        "count": 2472
      },
      {
        "ext": ".sig",
        "count": 1122
      },
      {
        "ext": ".appimage",
        "count": 572
      },
      {
        "ext": ".rpm",
        "count": 250
      },
      {
        "ext": ".deb",
        "count": 13
      }
    ]
  },
  {
    "date": "2025-12-01",
    "total": 62092,
    "formats": [
      {
        "ext": ".exe",
        "count": 40382
      },
      {
        "ext": ".asar",
        "count": 13007
      },
      {
        "ext": ".dmg",
        "count": 4136
      },
      {
        "ext": ".zip",
        "count": 2516
      },
      {
        "ext": ".sig",
        "count": 1122
      },
      {
        "ext": ".appimage",
        "count": 593
      },
      {
        "ext": ".rpm",
        "count": 318
      },
      {
        "ext": ".deb",
        "count": 18
      }
    ]
  },
  {
    "date": "2025-12-02",
    "total": 62442,
    "formats": [
      {
        "ext": ".exe",
        "count": 40575
      },
      {
        "ext": ".asar",
        "count": 13007
      },
      {
        "ext": ".dmg",
        "count": 4153
      },
      {
        "ext": ".zip",
        "count": 2552
      },
      {
        "ext": ".sig",
        "count": 1122
      },
      {
        "ext": ".appimage",
        "count": 618
      },
      {
        "ext": ".rpm",
        "count": 393
      },
      {
        "ext": ".deb",
        "count": 22
      }
    ]
  },
  {
    "date": "2025-12-03",
    "total": 62753,
    "formats": [
      {
        "ext": ".exe",
        "count": 40752
      },
      {
        "ext": ".asar",
        "count": 13007
      },
      {
        "ext": ".dmg",
        "count": 4162
      },
      {
        "ext": ".zip",
        "count": 2592
      },
      {
        "ext": ".sig",
        "count": 1122
      },
      {
        "ext": ".appimage",
        "count": 639
      },
      {
        "ext": ".rpm",
        "count": 457
      },
      {
        "ext": ".deb",
        "count": 22
      }
    ]
  },
  {
    "date": "2025-12-04",
    "total": 63118,
    "formats": [
      {
        "ext": ".exe",
        "count": 40954
      },
      {
        "ext": ".asar",
        "count": 13007
      },
      {
        "ext": ".dmg",
        "count": 4179
      },
      {
        "ext": ".zip",
        "count": 2656
      },
      {
        "ext": ".sig",
        "count": 1122
      },
      {
        "ext": ".appimage",
        "count": 656
      },
      {
        "ext": ".rpm",
        "count": 514
      },
      {
        "ext": ".deb",
        "count": 30
      }
    ]
  },
  {
    "date": "2025-12-05",
    "total": 63525,
    "formats": [
      {
        "ext": ".exe",
        "count": 41175
      },
      {
        "ext": ".asar",
        "count": 13007
      },
      {
        "ext": ".dmg",
        "count": 4197
      },
      {
        "ext": ".zip",
        "count": 2703
      },
      {
        "ext": ".sig",
        "count": 1122
      },
      {
        "ext": ".appimage",
        "count": 676
      },
      {
        "ext": ".rpm",
        "count": 614
      },
      {
        "ext": ".deb",
        "count": 31
      }
    ]
  },
  {
    "date": "2025-12-06",
    "total": 63961,
    "formats": [
      {
        "ext": ".exe",
        "count": 41427
      },
      {
        "ext": ".asar",
        "count": 13007
      },
      {
        "ext": ".dmg",
        "count": 4214
      },
      {
        "ext": ".zip",
        "count": 2752
      },
      {
        "ext": ".sig",
        "count": 1122
      },
      {
        "ext": ".rpm",
        "count": 707
      },
      {
        "ext": ".appimage",
        "count": 697
      },
      {
        "ext": ".deb",
        "count": 35
      }
    ]
  },
  {
    "date": "2025-12-07",
    "total": 64357,
    "formats": [
      {
        "ext": ".exe",
        "count": 41663
      },
      {
        "ext": ".asar",
        "count": 13007
      },
      {
        "ext": ".dmg",
        "count": 4229
      },
      {
        "ext": ".zip",
        "count": 2808
      },
      {
        "ext": ".sig",
        "count": 1122
      },
      {
        "ext": ".rpm",
        "count": 774
      },
      {
        "ext": ".appimage",
        "count": 718
      },
      {
        "ext": ".deb",
        "count": 36
      }
    ]
  },
  {
    "date": "2025-12-08",
    "total": 64778,
    "formats": [
      {
        "ext": ".exe",
        "count": 41916
      },
      {
        "ext": ".asar",
        "count": 13007
      },
      {
        "ext": ".dmg",
        "count": 4244
      },
      {
        "ext": ".zip",
        "count": 2860
      },
      {
        "ext": ".sig",
        "count": 1122
      },
      {
        "ext": ".rpm",
        "count": 844
      },
      {
        "ext": ".appimage",
        "count": 747
      },
      {
        "ext": ".deb",
        "count": 38
      }
    ]
  },
  {
    "date": "2025-12-09",
    "total": 65085,
    "formats": [
      {
        "ext": ".exe",
        "count": 42098
      },
      {
        "ext": ".asar",
        "count": 13007
      },
      {
        "ext": ".dmg",
        "count": 4258
      },
      {
        "ext": ".zip",
        "count": 2904
      },
      {
        "ext": ".sig",
        "count": 1122
      },
      {
        "ext": ".rpm",
        "count": 895
      },
      {
        "ext": ".appimage",
        "count": 763
      },
      {
        "ext": ".deb",
        "count": 38
      }
    ]
  },
  {
    "date": "2025-12-10",
    "total": 65403,
    "formats": [
      {
        "ext": ".exe",
        "count": 42295
      },
      {
        "ext": ".asar",
        "count": 13007
      },
      {
        "ext": ".dmg",
        "count": 4267
      },
      {
        "ext": ".zip",
        "count": 2938
      },
      {
        "ext": ".sig",
        "count": 1122
      },
      {
        "ext": ".rpm",
        "count": 953
      },
      {
        "ext": ".appimage",
        "count": 781
      },
      {
        "ext": ".deb",
        "count": 40
      }
    ]
  },
  {
    "date": "2025-12-11",
    "total": 65835,
    "formats": [
      {
        "ext": ".exe",
        "count": 42527
      },
      {
        "ext": ".asar",
        "count": 13007
      },
      {
        "ext": ".dmg",
        "count": 4284
      },
      {
        "ext": ".zip",
        "count": 3014
      },
      {
        "ext": ".sig",
        "count": 1122
      },
      {
        "ext": ".rpm",
        "count": 1025
      },
      {
        "ext": ".appimage",
        "count": 807
      },
      {
        "ext": ".deb",
        "count": 49
      }
    ]
  },
  {
    "date": "2025-12-12",
    "total": 66124,
    "formats": [
      {
        "ext": ".exe",
        "count": 42693
      },
      {
        "ext": ".asar",
        "count": 13007
      },
      {
        "ext": ".dmg",
        "count": 4291
      },
      {
        "ext": ".zip",
        "count": 3067
      },
      {
        "ext": ".sig",
        "count": 1122
      },
      {
        "ext": ".rpm",
        "count": 1067
      },
      {
        "ext": ".appimage",
        "count": 823
      },
      {
        "ext": ".deb",
        "count": 54
      }
    ]
  },
  {
    "date": "2025-12-13",
    "total": 66524,
    "formats": [
      {
        "ext": ".exe",
        "count": 42931
      },
      {
        "ext": ".asar",
        "count": 13007
      },
      {
        "ext": ".dmg",
        "count": 4307
      },
      {
        "ext": ".zip",
        "count": 3107
      },
      {
        "ext": ".rpm",
        "count": 1145
      },
      {
        "ext": ".sig",
        "count": 1122
      },
      {
        "ext": ".appimage",
        "count": 849
      },
      {
        "ext": ".deb",
        "count": 56
      }
    ]
  },
  {
    "date": "2025-12-14",
    "total": 66986,
    "formats": [
      {
        "ext": ".exe",
        "count": 43190
      },
      {
        "ext": ".asar",
        "count": 13007
      },
      {
        "ext": ".dmg",
        "count": 4328
      },
      {
        "ext": ".zip",
        "count": 3179
      },
      {
        "ext": ".rpm",
        "count": 1223
      },
      {
        "ext": ".sig",
        "count": 1122
      },
      {
        "ext": ".appimage",
        "count": 873
      },
      {
        "ext": ".deb",
        "count": 64
      }
    ]
  },
  {
    "date": "2025-12-15",
    "total": 67334,
    "formats": [
      {
        "ext": ".exe",
        "count": 43401
      },
      {
        "ext": ".asar",
        "count": 13007
      },
      {
        "ext": ".dmg",
        "count": 4346
      },
      {
        "ext": ".zip",
        "count": 3218
      },
      {
        "ext": ".rpm",
        "count": 1276
      },
      {
        "ext": ".sig",
        "count": 1122
      },
      {
        "ext": ".appimage",
        "count": 896
      },
      {
        "ext": ".deb",
        "count": 68
      }
    ]
  },
  {
    "date": "2025-12-16",
    "total": 67620,
    "formats": [
      {
        "ext": ".exe",
        "count": 43579
      },
      {
        "ext": ".asar",
        "count": 13007
      },
      {
        "ext": ".dmg",
        "count": 4357
      },
      {
        "ext": ".zip",
        "count": 3246
      },
      {
        "ext": ".rpm",
        "count": 1321
      },
      {
        "ext": ".sig",
        "count": 1122
      },
      {
        "ext": ".appimage",
        "count": 918
      },
      {
        "ext": ".deb",
        "count": 70
      }
    ]
  },
  {
    "date": "2025-12-17",
    "total": 67805,
    "formats": [
      {
        "ext": ".exe",
        "count": 43700
      },
      {
        "ext": ".asar",
        "count": 13007
      },
      {
        "ext": ".dmg",
        "count": 4362
      },
      {
        "ext": ".zip",
        "count": 3264
      },
      {
        "ext": ".rpm",
        "count": 1348
      },
      {
        "ext": ".sig",
        "count": 1122
      },
      {
        "ext": ".appimage",
        "count": 930
      },
      {
        "ext": ".deb",
        "count": 72
      }
    ]
  },
  {
    "date": "2025-12-18",
    "total": 67959,
    "formats": [
      {
        "ext": ".exe",
        "count": 43796
      },
      {
        "ext": ".asar",
        "count": 13007
      },
      {
        "ext": ".dmg",
        "count": 4367
      },
      {
        "ext": ".zip",
        "count": 3277
      },
      {
        "ext": ".rpm",
        "count": 1375
      },
      {
        "ext": ".sig",
        "count": 1122
      },
      {
        "ext": ".appimage",
        "count": 941
      },
      {
        "ext": ".deb",
        "count": 74
      }
    ]
  },
  {
    "date": "2025-12-19",
    "total": 68244,
    "formats": [
      {
        "ext": ".exe",
        "count": 43969
      },
      {
        "ext": ".asar",
        "count": 13007
      },
      {
        "ext": ".dmg",
        "count": 4382
      },
      {
        "ext": ".zip",
        "count": 3302
      },
      {
        "ext": ".rpm",
        "count": 1426
      },
      {
        "ext": ".sig",
        "count": 1122
      },
      {
        "ext": ".appimage",
        "count": 958
      },
      {
        "ext": ".deb",
        "count": 78
      }
    ]
  },
  {
    "date": "2025-12-20",
    "total": 68447,
    "formats": [
      {
        "ext": ".exe",
        "count": 44106
      },
      {
        "ext": ".asar",
        "count": 13007
      },
      {
        "ext": ".dmg",
        "count": 4388
      },
      {
        "ext": ".zip",
        "count": 3322
      },
      {
        "ext": ".rpm",
        "count": 1458
      },
      {
        "ext": ".sig",
        "count": 1122
      },
      {
        "ext": ".appimage",
        "count": 963
      },
      {
        "ext": ".deb",
        "count": 81
      }
    ]
  },
  {
    "date": "2025-12-21",
    "total": 68892,
    "formats": [
      {
        "ext": ".exe",
        "count": 44333
      },
      {
        "ext": ".asar",
        "count": 13013
      },
      {
        "ext": ".dmg",
        "count": 4438
      },
      {
        "ext": ".zip",
        "count": 3391
      },
      {
        "ext": ".rpm",
        "count": 1499
      },
      {
        "ext": ".sig",
        "count": 1122
      },
      {
        "ext": ".appimage",
        "count": 1009
      },
      {
        "ext": ".deb",
        "count": 87
      }
    ]
  },
  {
    "date": "2025-12-22",
    "total": 69067,
    "formats": [
      {
        "ext": ".exe",
        "count": 44459
      },
      {
        "ext": ".asar",
        "count": 13013
      },
      {
        "ext": ".dmg",
        "count": 4447
      },
      {
        "ext": ".zip",
        "count": 3403
      },
      {
        "ext": ".rpm",
        "count": 1518
      },
      {
        "ext": ".sig",
        "count": 1122
      },
      {
        "ext": ".appimage",
        "count": 1017
      },
      {
        "ext": ".deb",
        "count": 88
      }
    ]
  },
  {
    "date": "2025-12-23",
    "total": 69293,
    "formats": [
      {
        "ext": ".exe",
        "count": 44585
      },
      {
        "ext": ".asar",
        "count": 13013
      },
      {
        "ext": ".dmg",
        "count": 4452
      },
      {
        "ext": ".zip",
        "count": 3438
      },
      {
        "ext": ".rpm",
        "count": 1562
      },
      {
        "ext": ".sig",
        "count": 1122
      },
      {
        "ext": ".appimage",
        "count": 1025
      },
      {
        "ext": ".deb",
        "count": 96
      }
    ]
  },
  {
    "date": "2025-12-24",
    "total": 69585,
    "formats": [
      {
        "ext": ".exe",
        "count": 44755
      },
      {
        "ext": ".asar",
        "count": 13013
      },
      {
        "ext": ".dmg",
        "count": 4466
      },
      {
        "ext": ".zip",
        "count": 3471
      },
      {
        "ext": ".rpm",
        "count": 1620
      },
      {
        "ext": ".sig",
        "count": 1122
      },
      {
        "ext": ".appimage",
        "count": 1038
      },
      {
        "ext": ".deb",
        "count": 100
      }
    ]
  },
  {
    "date": "2025-12-25",
    "total": 69785,
    "formats": [
      {
        "ext": ".exe",
        "count": 44870
      },
      {
        "ext": ".asar",
        "count": 13013
      },
      {
        "ext": ".dmg",
        "count": 4477
      },
      {
        "ext": ".zip",
        "count": 3492
      },
      {
        "ext": ".rpm",
        "count": 1661
      },
      {
        "ext": ".sig",
        "count": 1122
      },
      {
        "ext": ".appimage",
        "count": 1047
      },
      {
        "ext": ".deb",
        "count": 103
      }
    ]
  },
  {
    "date": "2025-12-26",
    "total": 69988,
    "formats": [
      {
        "ext": ".exe",
        "count": 44991
      },
      {
        "ext": ".asar",
        "count": 13013
      },
      {
        "ext": ".dmg",
        "count": 4486
      },
      {
        "ext": ".zip",
        "count": 3515
      },
      {
        "ext": ".rpm",
        "count": 1691
      },
      {
        "ext": ".sig",
        "count": 1122
      },
      {
        "ext": ".appimage",
        "count": 1064
      },
      {
        "ext": ".deb",
        "count": 106
      }
    ]
  },
  {
    "date": "2025-12-27",
    "total": 70201,
    "formats": [
      {
        "ext": ".exe",
        "count": 45122
      },
      {
        "ext": ".asar",
        "count": 13013
      },
      {
        "ext": ".dmg",
        "count": 4490
      },
      {
        "ext": ".zip",
        "count": 3546
      },
      {
        "ext": ".rpm",
        "count": 1718
      },
      {
        "ext": ".sig",
        "count": 1122
      },
      {
        "ext": ".appimage",
        "count": 1079
      },
      {
        "ext": ".deb",
        "count": 111
      }
    ]
  },
  {
    "date": "2025-12-28",
    "total": 70349,
    "formats": [
      {
        "ext": ".exe",
        "count": 45227
      },
      {
        "ext": ".asar",
        "count": 13013
      },
      {
        "ext": ".dmg",
        "count": 4495
      },
      {
        "ext": ".zip",
        "count": 3559
      },
      {
        "ext": ".rpm",
        "count": 1738
      },
      {
        "ext": ".sig",
        "count": 1122
      },
      {
        "ext": ".appimage",
        "count": 1083
      },
      {
        "ext": ".deb",
        "count": 112
      }
    ]
  },
  {
    "date": "2025-12-29",
    "total": 70477,
    "formats": [
      {
        "ext": ".exe",
        "count": 45325
      },
      {
        "ext": ".asar",
        "count": 13013
      },
      {
        "ext": ".dmg",
        "count": 4497
      },
      {
        "ext": ".zip",
        "count": 3571
      },
      {
        "ext": ".rpm",
        "count": 1749
      },
      {
        "ext": ".sig",
        "count": 1122
      },
      {
        "ext": ".appimage",
        "count": 1085
      },
      {
        "ext": ".deb",
        "count": 115
      }
    ]
  },
  {
    "date": "2025-12-30",
    "total": 70672,
    "formats": [
      {
        "ext": ".exe",
        "count": 45440
      },
      {
        "ext": ".asar",
        "count": 13013
      },
      {
        "ext": ".dmg",
        "count": 4502
      },
      {
        "ext": ".zip",
        "count": 3594
      },
      {
        "ext": ".rpm",
        "count": 1794
      },
      {
        "ext": ".sig",
        "count": 1122
      },
      {
        "ext": ".appimage",
        "count": 1092
      },
      {
        "ext": ".deb",
        "count": 115
      }
    ]
  },
  {
    "date": "2025-12-31",
    "total": 70909,
    "formats": [
      {
        "ext": ".exe",
        "count": 45575
      },
      {
        "ext": ".asar",
        "count": 13013
      },
      {
        "ext": ".dmg",
        "count": 4507
      },
      {
        "ext": ".zip",
        "count": 3624
      },
      {
        "ext": ".rpm",
        "count": 1846
      },
      {
        "ext": ".sig",
        "count": 1122
      },
      {
        "ext": ".appimage",
        "count": 1104
      },
      {
        "ext": ".deb",
        "count": 118
      }
    ]
  },
  {
    "date": "2026-01-01",
    "total": 71127,
    "formats": [
      {
        "ext": ".exe",
        "count": 45709
      },
      {
        "ext": ".asar",
        "count": 13013
      },
      {
        "ext": ".dmg",
        "count": 4513
      },
      {
        "ext": ".zip",
        "count": 3639
      },
      {
        "ext": ".rpm",
        "count": 1891
      },
      {
        "ext": ".sig",
        "count": 1122
      },
      {
        "ext": ".appimage",
        "count": 1121
      },
      {
        "ext": ".deb",
        "count": 119
      }
    ]
  },
  {
    "date": "2026-01-02",
    "total": 71403,
    "formats": [
      {
        "ext": ".exe",
        "count": 45851
      },
      {
        "ext": ".asar",
        "count": 13013
      },
      {
        "ext": ".dmg",
        "count": 4525
      },
      {
        "ext": ".zip",
        "count": 3694
      },
      {
        "ext": ".rpm",
        "count": 1947
      },
      {
        "ext": ".appimage",
        "count": 1131
      },
      {
        "ext": ".sig",
        "count": 1122
      },
      {
        "ext": ".deb",
        "count": 120
      }
    ]
  },
  {
    "date": "2026-01-03",
    "total": 71704,
    "formats": [
      {
        "ext": ".exe",
        "count": 46010
      },
      {
        "ext": ".asar",
        "count": 13013
      },
      {
        "ext": ".dmg",
        "count": 4531
      },
      {
        "ext": ".zip",
        "count": 3746
      },
      {
        "ext": ".rpm",
        "count": 2014
      },
      {
        "ext": ".appimage",
        "count": 1146
      },
      {
        "ext": ".sig",
        "count": 1122
      },
      {
        "ext": ".deb",
        "count": 122
      }
    ]
  },
  {
    "date": "2026-01-04",
    "total": 71980,
    "formats": [
      {
        "ext": ".exe",
        "count": 46171
      },
      {
        "ext": ".asar",
        "count": 13013
      },
      {
        "ext": ".dmg",
        "count": 4537
      },
      {
        "ext": ".zip",
        "count": 3776
      },
      {
        "ext": ".rpm",
        "count": 2074
      },
      {
        "ext": ".appimage",
        "count": 1163
      },
      {
        "ext": ".sig",
        "count": 1122
      },
      {
        "ext": ".deb",
        "count": 124
      }
    ]
  },
  {
    "date": "2026-01-05",
    "total": 72313,
    "formats": [
      {
        "ext": ".exe",
        "count": 46357
      },
      {
        "ext": ".asar",
        "count": 13013
      },
      {
        "ext": ".dmg",
        "count": 4547
      },
      {
        "ext": ".zip",
        "count": 3824
      },
      {
        "ext": ".rpm",
        "count": 2148
      },
      {
        "ext": ".appimage",
        "count": 1176
      },
      {
        "ext": ".sig",
        "count": 1122
      },
      {
        "ext": ".deb",
        "count": 126
      }
    ]
  },
  {
    "date": "2026-01-06",
    "total": 72640,
    "formats": [
      {
        "ext": ".exe",
        "count": 46528
      },
      {
        "ext": ".asar",
        "count": 13013
      },
      {
        "ext": ".dmg",
        "count": 4562
      },
      {
        "ext": ".zip",
        "count": 3877
      },
      {
        "ext": ".rpm",
        "count": 2204
      },
      {
        "ext": ".appimage",
        "count": 1200
      },
      {
        "ext": ".sig",
        "count": 1122
      },
      {
        "ext": ".deb",
        "count": 134
      }
    ]
  },
  {
    "date": "2026-01-07",
    "total": 72967,
    "formats": [
      {
        "ext": ".exe",
        "count": 46699
      },
      {
        "ext": ".asar",
        "count": 13013
      },
      {
        "ext": ".dmg",
        "count": 4575
      },
      {
        "ext": ".zip",
        "count": 3929
      },
      {
        "ext": ".rpm",
        "count": 2272
      },
      {
        "ext": ".appimage",
        "count": 1218
      },
      {
        "ext": ".sig",
        "count": 1122
      },
      {
        "ext": ".deb",
        "count": 139
      }
    ]
  },
  {
    "date": "2026-01-08",
    "total": 73325,
    "formats": [
      {
        "ext": ".exe",
        "count": 46908
      },
      {
        "ext": ".asar",
        "count": 13013
      },
      {
        "ext": ".dmg",
        "count": 4584
      },
      {
        "ext": ".zip",
        "count": 3975
      },
      {
        "ext": ".rpm",
        "count": 2346
      },
      {
        "ext": ".appimage",
        "count": 1236
      },
      {
        "ext": ".sig",
        "count": 1122
      },
      {
        "ext": ".deb",
        "count": 141
      }
    ]
  },
  {
    "date": "2026-01-09",
    "total": 73667,
    "formats": [
      {
        "ext": ".exe",
        "count": 47108
      },
      {
        "ext": ".asar",
        "count": 13013
      },
      {
        "ext": ".dmg",
        "count": 4594
      },
      {
        "ext": ".zip",
        "count": 4018
      },
      {
        "ext": ".rpm",
        "count": 2410
      },
      {
        "ext": ".appimage",
        "count": 1257
      },
      {
        "ext": ".sig",
        "count": 1122
      },
      {
        "ext": ".deb",
        "count": 145
      }
    ]
  },
  {
    "date": "2026-01-10",
    "total": 74058,
    "formats": [
      {
        "ext": ".exe",
        "count": 47328
      },
      {
        "ext": ".asar",
        "count": 13013
      },
      {
        "ext": ".dmg",
        "count": 4606
      },
      {
        "ext": ".zip",
        "count": 4072
      },
      {
        "ext": ".rpm",
        "count": 2490
      },
      {
        "ext": ".appimage",
        "count": 1278
      },
      {
        "ext": ".sig",
        "count": 1122
      },
      {
        "ext": ".deb",
        "count": 149
      }
    ]
  },
  {
    "date": "2026-01-11",
    "total": 74407,
    "formats": [
      {
        "ext": ".exe",
        "count": 47517
      },
      {
        "ext": ".asar",
        "count": 13013
      },
      {
        "ext": ".dmg",
        "count": 4622
      },
      {
        "ext": ".zip",
        "count": 4116
      },
      {
        "ext": ".rpm",
        "count": 2563
      },
      {
        "ext": ".appimage",
        "count": 1302
      },
      {
        "ext": ".sig",
        "count": 1122
      },
      {
        "ext": ".deb",
        "count": 152
      }
    ]
  },
  {
    "date": "2026-01-12",
    "total": 74702,
    "formats": [
      {
        "ext": ".exe",
        "count": 47684
      },
      {
        "ext": ".asar",
        "count": 13013
      },
      {
        "ext": ".dmg",
        "count": 4635
      },
      {
        "ext": ".zip",
        "count": 4151
      },
      {
        "ext": ".rpm",
        "count": 2620
      },
      {
        "ext": ".appimage",
        "count": 1321
      },
      {
        "ext": ".sig",
        "count": 1122
      },
      {
        "ext": ".deb",
        "count": 156
      }
    ]
  },
  {
    "date": "2026-01-13",
    "total": 74938,
    "formats": [
      {
        "ext": ".exe",
        "count": 47819
      },
      {
        "ext": ".asar",
        "count": 13013
      },
      {
        "ext": ".dmg",
        "count": 4642
      },
      {
        "ext": ".zip",
        "count": 4183
      },
      {
        "ext": ".rpm",
        "count": 2668
      },
      {
        "ext": ".appimage",
        "count": 1335
      },
      {
        "ext": ".sig",
        "count": 1122
      },
      {
        "ext": ".deb",
        "count": 156
      }
    ]
  },
  {
    "date": "2026-01-14",
    "total": 75268,
    "formats": [
      {
        "ext": ".exe",
        "count": 48005
      },
      {
        "ext": ".asar",
        "count": 13013
      },
      {
        "ext": ".dmg",
        "count": 4659
      },
      {
        "ext": ".zip",
        "count": 4216
      },
      {
        "ext": ".rpm",
        "count": 2735
      },
      {
        "ext": ".appimage",
        "count": 1358
      },
      {
        "ext": ".sig",
        "count": 1122
      },
      {
        "ext": ".deb",
        "count": 160
      }
    ]
  }
]